nutsflow/__init__.py
nutsflow/base.py
nutsflow/common.py
nutsflow/config.py
nutsflow/factory.py
nutsflow/function.py
nutsflow/iterfunction.py
nutsflow/processor.py
nutsflow/sink.py
nutsflow/source.py
nutsflow/underscore.py
nutsflow/examples/__init__.py
nutsflow/examples/examples.py
tests/__init__.py
tests/data/arab2num.csv
tests/data/config.yaml
tests/data/configuration.json
tests/data/configuration.yaml
tests/data/data.csv
tests/data/data.tsv
tests/data/numbers.txt
tests/nutsflow/__init__.py
tests/nutsflow/test_base.py
tests/nutsflow/test_common.py
tests/nutsflow/test_config.py
tests/nutsflow/test_factory.py
tests/nutsflow/test_function.py
tests/nutsflow/test_iterfunction.py
tests/nutsflow/test_processor.py
tests/nutsflow/test_sink.py
tests/nutsflow/test_source.py
tests/nutsflow/test_underscore.py
tests/nutsflow/examples/__init__.py
tests/nutsflow/examples/test_examples.py
nutsflow-1.2.3.dist-info/LICENSE
nutsflow-1.2.3.dist-info/METADATA
nutsflow-1.2.3.dist-info/WHEEL
nutsflow-1.2.3.dist-info/top_level.txt
nutsflow-1.2.3.dist-info/RECORD
