Metadata-Version: 2.1
Name: nutsflow
Version: 1.2.3
Summary: A simple data-flow framework based on iterator chaining
Home-page: https://maet3608.github.io/nuts-flow
Author: Stefan Maetschke
Author-email: stefan.maetschke@gmail.com
License: Apache Software License (http://www.apache.org/licenses/LICENSE-2.0)
Download-URL: https://github.com/maet3608/nuts-flow
Platform: any
Classifier: Development Status :: 5 - Production/Stable
Classifier: Programming Language :: Python :: 2.7
Classifier: Programming Language :: Python :: 3.5
Classifier: Programming Language :: Python :: 3.6
Classifier: Programming Language :: Python :: 3.7
Classifier: Programming Language :: Python :: 3.8
Classifier: Programming Language :: Python :: 3.9
Classifier: Natural Language :: English
Classifier: Intended Audience :: Developers
Classifier: Intended Audience :: Science/Research
Classifier: License :: OSI Approved :: Apache Software License
Classifier: Operating System :: OS Independent
Classifier: Topic :: Software Development :: Libraries :: Python Modules
Requires-Dist: six (>=1.10.0)
Requires-Dist: pyyaml (>=3.12)
